LICENCE
README.md
setup.py
EncodingExplosion/__init__.py
EncodingExplosion.egg-info/PKG-INFO
EncodingExplosion.egg-info/SOURCES.txt
EncodingExplosion.egg-info/dependency_links.txt
EncodingExplosion.egg-info/requires.txt
EncodingExplosion.egg-info/top_level.txt