Metadata-Version: 2.4
Name: EncodingExplosion
Version: 0.0.1
Summary: A tool let you know you file encoding.
Home-page: https://github.com/wayne931121/EncodingExplosion
Author: wayne931121
Author-email: 
License: Attribution 4.0 International, Copyright (c) 2025 Wayne931121.
Classifier: Programming Language :: Python :: 3
Classifier: Operating System :: OS Independent
Requires-Python: >=3.0
License-File: LICENCE
Requires-Dist: chardet
Dynamic: author
Dynamic: classifier
Dynamic: description
Dynamic: description-content-type
Dynamic: home-page
Dynamic: license
Dynamic: license-file
Dynamic: requires-dist
Dynamic: requires-python
Dynamic: summary
